seppelsmother/__init__.py
seppelsmother/control.py
seppelsmother/nose_plugin.py
seppelsmother/pytest_plugin.py
seppelsmother/python.py
seppelsmother/tests/__init__.py
seppelsmother/tests/demo.py
seppelsmother/tests/demo_testsuite.py
seppelsmother/tests/test_controller.py
seppelsmother/tests/test_plugins.py
seppelsmother/tests/test_python.py
seppelsmother/tests/utils.py
seppelsmother-0.2.dist-info/DESCRIPTION.rst
seppelsmother-0.2.dist-info/METADATA
seppelsmother-0.2.dist-info/RECORD
seppelsmother-0.2.dist-info/WHEEL
seppelsmother-0.2.dist-info/entry_points.txt
seppelsmother-0.2.dist-info/metadata.json
seppelsmother-0.2.dist-info/top_level.txt
